MANIFEST.in
setup.py
./Notes/window.py
Notes/__init__.py
Notes/main.py
Notes/window.py
Notes/imgs/center-alignment.png
Notes/imgs/left-alignment.png
Notes/imgs/minus.png
Notes/imgs/plus.png
Notes/imgs/right-alignment.png
your_notes.egg-info/PKG-INFO
your_notes.egg-info/SOURCES.txt
your_notes.egg-info/dependency_links.txt
your_notes.egg-info/entry_points.txt
your_notes.egg-info/not-zip-safe
your_notes.egg-info/requires.txt
your_notes.egg-info/top_level.txt