Metadata-Version: 1.1
Name: your-notes
Version: 0.1
Summary: a)
Home-page: http://github.com/5hy0w1/Notes
Author: Artem 5hy0w1
Author-email: 5hy0w1@mail.ru
License: GNU
Keywords: notes
Platform: UNKNOWN
Classifier: Development Status :: 4 - Beta
Classifier: Environment :: X11 Applications :: GTK
Classifier: Intended Audience :: End Users/Desktop
Classifier: Intended Audience :: Developers
Classifier: License :: OSI Approved :: GNU General Public License (GPL)
Classifier: Operating System :: POSIX :: Linux
Classifier: Programming Language :: Python
Classifier: Topic :: Desktop Environment
Classifier: Topic :: Text Processing :: Fonts
